demure_logger/__init__.py
demure_logger/__main__.py
demure_logger/configuration/__init__.py
demure_logger/configuration/exceptions.py
demure_logger/format/__init__.py
demure_logger/format/text/__init__.py
demure_logger/format/text/colors/__init__.py
demure_logger/format/text/colors/controller.py
demure_logger/format/text/colors/decorators.py
demure_logger/format/text/colors/exceptions.py
demure_logger/handlers/__init__.py
demure_logger/handlers/basic.py
demure_logger/handlers/pipe.py
demure_logger/log/__init__.py
demure_logger/log/exceptions.py
demure_logger/log/levels.py
demure_logger/log/message/__init__.py
demure_logger/log/message/exceptions.py
demure_logger/log/message/field.py
demure_logger/structure/__init__.py
demure_logger/structure/queue.py
demure_logger/types/__init__.py
demure_logger/types/simple.py
demure_logger/utils/__init__.py
demure_logger/utils/cls.py
demure_logger/utils/interval.py
demure_logger/utils/list.py
demure_logger/writer/__init__.py
demure_loggers/__init__.py
demure_loggers/console/__init__.py
demure_loggers/console/writer.py
demure_loggers/console/message/__init__.py
demure_loggers/console/message/field/__init__.py
demure_loggers/file/__init__.py
demure_loggers/file/writer.py
demure_loggers/file/message/__init__.py
demure_loggers/json/__init__.py
demure_loggers/json/writer.py
demure_loggers/json/format/__init__.py
demure_loggers/json/message/__init__.py
demure_logger-0.9.1.dist-info/LICENSE.txt
demure_logger-0.9.1.dist-info/METADATA
demure_logger-0.9.1.dist-info/WHEEL
demure_logger-0.9.1.dist-info/top_level.txt
demure_logger-0.9.1.dist-info/RECORD
