Metadata-Version: 2.1
Name: demure-logger
Version: 0.9.1
Summary: Simple but customize captcha generator( image + voice )
Home-page: https://github.com/grdvsng/demure_logger
Author: Trishkin Sergey
Author-email: grdvsng@gmail.com
License: UNKNOWN
Platform: UNKNOWN
Classifier: Programming Language :: Python :: 3.8
Classifier: License :: OSI Approved :: GNU General Public License v3 or later (GPLv3+)
Requires-Python: >=3.8
License-File: LICENSE.txt
Requires-Dist: anyio (>=3.5.0)
Requires-Dist: asgiref (>=3.5.0)
Requires-Dist: atomicwrites (>=1.4.0)
Requires-Dist: attrs (>=21.4.0)
Requires-Dist: click (>=8.1.2)
Requires-Dist: colorama (>=0.4.4)
Requires-Dist: fastapi (>=0.75.1)
Requires-Dist: grep (>=0.3.2)
Requires-Dist: h11 (>=0.13.0)
Requires-Dist: httptools (>=0.4.0)
Requires-Dist: idna (>=3.3)
Requires-Dist: iniconfig (>=1.1.1)
Requires-Dist: janus (>=1.0.0)
Requires-Dist: lazyme (>=0.0.27)
Requires-Dist: lorem (>=0.1.1)
Requires-Dist: packaging (>=21.3)
Requires-Dist: peewee (>=3.14.10)
Requires-Dist: pluggy (>=1.0.0)
Requires-Dist: psutil (>=5.9.0)
Requires-Dist: py (>=1.11.0)
Requires-Dist: pydantic (>=1.9.0)
Requires-Dist: pyparsing (>=3.0.8)
Requires-Dist: pytest (>=7.1.1)
Requires-Dist: python-dateutil (>=2.8.2)
Requires-Dist: python-dotenv (>=0.20.0)
Requires-Dist: python-multipart (>=0.0.5)
Requires-Dist: PyYAML (>=6.0)
Requires-Dist: six (>=1.16.0)
Requires-Dist: sniffio (>=1.2.0)
Requires-Dist: starlette (>=0.17.1)
Requires-Dist: tomli (>=2.0.1)
Requires-Dist: typing-extensions (>=4.1.1)
Requires-Dist: uvicorn (>=0.17.6)
Requires-Dist: watchgod (>=0.8.2)
Requires-Dist: websockets (>=10.2)
